<?xml version='1.0' encoding='utf-8'?>
<vysledky>
  <obec>
    <Číslo obce>598925</Číslo obce>
    <Název obce>Albrechtice</Název obce>
    <Voliči>3173</Voliči>
    <Vydané obálky>1957</Vydané obálky>
    <Platné hlasy>1944</Platné hlasy>
    <Občanská demokratická strana>109</Občanská demokratická strana>
    <Řád národa - Vlastenecká unie>4</Řád národa - Vlastenecká unie>
    <CESTA ODPOVĚDNÉ SPOLEČNOSTI>2</CESTA ODPOVĚDNÉ SPOLEČNOSTI>
    <Česká str.sociálně demokrat.>181</Česká str.sociálně demokrat.>
    <Radostné Česko>2</Radostné Česko>
    <STAROSTOVÉ A NEZÁVISLÍ>131</STAROSTOVÉ A NEZÁVISLÍ>
    <Komunistická str.Čech a Moravy>211</Komunistická str.Čech a Moravy>
    <Strana zelených>15</Strana zelených>
    <ROZUMNÍ-stop migraci,diktát.EU>22</ROZUMNÍ-stop migraci,diktát.EU>
    <Strana svobodných občanů>12</Strana svobodných občanů>
    <Blok proti islam.-Obran.domova>1</Blok proti islam.-Obran.domova>
    <Občanská demokratická aliance>3</Občanská demokratická aliance>
    <Česká pirátská strana>139</Česká pirátská strana>
    <Česká národní fronta>0</Česká národní fronta>
    <Referendum o Evropské unii>5</Referendum o Evropské unii>
    <TOP 09>25</TOP 09>
    <ANO 2011>635</ANO 2011>
    <Dobrá volba 2016>1</Dobrá volba 2016>
    <SPR-Republ.str.Čsl. M.Sládka>1</SPR-Republ.str.Čsl. M.Sládka>
    <Křesť.demokr.unie-Čs.str.lid.>174</Křesť.demokr.unie-Čs.str.lid.>
    <Česká strana národně sociální>0</Česká strana národně sociální>
    <REALISTÉ>10</REALISTÉ>
    <SPORTOVCI>1</SPORTOVCI>
    <Dělnic.str.sociální spravedl.>0</Dělnic.str.sociální spravedl.>
    <Svob.a př.dem.-T.Okamura (SPD)>255</Svob.a př.dem.-T.Okamura (SPD)>
    <Strana Práv Občanů>5</Strana Práv Občanů>
  </obec>
  <obec>
    <Číslo obce>599051</Číslo obce>
    <Název obce>Bohumín</Název obce>
    <Voliči>17613</Voliči>
    <Vydané obálky>9040</Vydané obálky>
    <Platné hlasy>8973</Platné hlasy>
    <Občanská demokratická strana>579</Občanská demokratická strana>
    <Řád národa - Vlastenecká unie>12</Řád národa - Vlastenecká unie>
    <CESTA ODPOVĚDNÉ SPOLEČNOSTI>4</CESTA ODPOVĚDNÉ SPOLEČNOSTI>
    <Česká str.sociálně demokrat.>1241</Česká str.sociálně demokrat.>
    <Radostné Česko>9</Radostné Česko>
    <STAROSTOVÉ A NEZÁVISLÍ>133</STAROSTOVÉ A NEZÁVISLÍ>
    <Komunistická str.Čech a Moravy>821</Komunistická str.Čech a Moravy>
    <Strana zelených>85</Strana zelených>
    <ROZUMNÍ-stop migraci,diktát.EU>91</ROZUMNÍ-stop migraci,diktát.EU>
    <Strana svobodných občanů>87</Strana svobodných občanů>
    <Blok proti islam.-Obran.domova>7</Blok proti islam.-Obran.domova>
    <Občanská demokratická aliance>6</Občanská demokratická aliance>
    <Česká pirátská strana>641</Česká pirátská strana>
    <Česká národní fronta>0</Česká národní fronta>
    <Referendum o Evropské unii>12</Referendum o Evropské unii>
    <TOP 09>119</TOP 09>
    <ANO 2011>3157</ANO 2011>
    <Dobrá volba 2016>18</Dobrá volba 2016>
    <SPR-Republ.str.Čsl. M.Sládka>33</SPR-Republ.str.Čsl. M.Sládka>
    <Křesť.demokr.unie-Čs.str.lid.>305</Křesť.demokr.unie-Čs.str.lid.>
    <Česká strana národně sociální>3</Česká strana národně sociální>
    <REALISTÉ>55</REALISTÉ>
    <SPORTOVCI>14</SPORTOVCI>
    <Dělnic.str.sociální spravedl.>25</Dělnic.str.sociální spravedl.>
    <Svob.a př.dem.-T.Okamura (SPD)>1478</Svob.a př.dem.-T.Okamura (SPD)>
    <Strana Práv Občanů>38</Strana Práv Občanů>
  </obec>
  <obec>
    <Číslo obce>598933</Číslo obce>
    <Název obce>Český Těšín</Název obce>
    <Voliči>19635</Voliči>
    <Vydané obálky>10429</Vydané obálky>
    <Platné hlasy>10361</Platné hlasy>
    <Občanská demokratická strana>698</Občanská demokratická strana>
    <Řád národa - Vlastenecká unie>15</Řád národa - Vlastenecká unie>
    <CESTA ODPOVĚDNÉ SPOLEČNOSTI>4</CESTA ODPOVĚDNÉ SPOLEČNOSTI>
    <Česká str.sociálně demokrat.>877</Česká str.sociálně demokrat.>
    <Radostné Česko>12</Radostné Česko>
    <STAROSTOVÉ A NEZÁVISLÍ>192</STAROSTOVÉ A NEZÁVISLÍ>
    <Komunistická str.Čech a Moravy>760</Komunistická str.Čech a Moravy>
    <Strana zelených>129</Strana zelených>
    <ROZUMNÍ-stop migraci,diktát.EU>83</ROZUMNÍ-stop migraci,diktát.EU>
    <Strana svobodných občanů>107</Strana svobodných občanů>
    <Blok proti islam.-Obran.domova>7</Blok proti islam.-Obran.domova>
    <Občanská demokratická aliance>6</Občanská demokratická aliance>
    <Česká pirátská strana>828</Česká pirátská strana>
    <Česká národní fronta>0</Česká národní fronta>
    <Referendum o Evropské unii>5</Referendum o Evropské unii>
    <TOP 09>214</TOP 09>
    <ANO 2011>3597</ANO 2011>
    <Dobrá volba 2016>12</Dobrá volba 2016>
    <SPR-Republ.str.Čsl. M.Sládka>19</SPR-Republ.str.Čsl. M.Sládka>
    <Křesť.demokr.unie-Čs.str.lid.>1310</Křesť.demokr.unie-Čs.str.lid.>
    <Česká strana národně sociální>3</Česká strana národně sociální>
    <REALISTÉ>41</REALISTÉ>
    <SPORTOVCI>22</SPORTOVCI>
    <Dělnic.str.sociální spravedl.>16</Dělnic.str.sociální spravedl.>
    <Svob.a př.dem.-T.Okamura (SPD)>1365</Svob.a př.dem.-T.Okamura (SPD)>
    <Strana Práv Občanů>39</Strana Práv Občanů>
  </obec>
  <obec>
    <Číslo obce>598941</Číslo obce>
    <Název obce>Dětmarovice</Název obce>
    <Voliči>3507</Voliči>
    <Vydané obálky>2061</Vydané obálky>
    <Platné hlasy>2048</Platné hlasy>
    <Občanská demokratická strana>148</Občanská demokratická strana>
    <Řád národa - Vlastenecká unie>3</Řád národa - Vlastenecká unie>
    <CESTA ODPOVĚDNÉ SPOLEČNOSTI>1</CESTA ODPOVĚDNÉ SPOLEČNOSTI>
    <Česká str.sociálně demokrat.>161</Česká str.sociálně demokrat.>
    <Radostné Česko>4</Radostné Česko>
    <STAROSTOVÉ A NEZÁVISLÍ>46</STAROSTOVÉ A NEZÁVISLÍ>
    <Komunistická str.Čech a Moravy>241</Komunistická str.Čech a Moravy>
    <Strana zelených>12</Strana zelených>
    <ROZUMNÍ-stop migraci,diktát.EU>7</ROZUMNÍ-stop migraci,diktát.EU>
    <Strana svobodných občanů>18</Strana svobodných občanů>
    <Blok proti islam.-Obran.domova>0</Blok proti islam.-Obran.domova>
    <Občanská demokratická aliance>3</Občanská demokratická aliance>
    <Česká pirátská strana>153</Česká pirátská strana>
    <Česká národní fronta>0</Česká národní fronta>
    <Referendum o Evropské unii>1</Referendum o Evropské unii>
    <TOP 09>19</TOP 09>
    <ANO 2011>816</ANO 2011>
    <Dobrá volba 2016>4</Dobrá volba 2016>
    <SPR-Republ.str.Čsl. M.Sládka>4</SPR-Republ.str.Čsl. M.Sládka>
    <Křesť.demokr.unie-Čs.str.lid.>66</Křesť.demokr.unie-Čs.str.lid.>
    <Česká strana národně sociální>0</Česká strana národně sociální>
    <REALISTÉ>8</REALISTÉ>
    <SPORTOVCI>3</SPORTOVCI>
    <Dělnic.str.sociální spravedl.>6</Dělnic.str.sociální spravedl.>
    <Svob.a př.dem.-T.Okamura (SPD)>307</Svob.a př.dem.-T.Okamura (SPD)>
    <Strana Práv Občanů>17</Strana Práv Občanů>
  </obec>
  <obec>
    <Číslo obce>598968</Číslo obce>
    <Název obce>Dolní Lutyně</Název obce>
    <Voliči>4299</Voliči>
    <Vydané obálky>2568</Vydané obálky>
    <Platné hlasy>2547</Platné hlasy>
    <Občanská demokratická strana>157</Občanská demokratická strana>
    <Řád národa - Vlastenecká unie>3</Řád národa - Vlastenecká unie>
    <CESTA ODPOVĚDNÉ SPOLEČNOSTI>3</CESTA ODPOVĚDNÉ SPOLEČNOSTI>
    <Česká str.sociálně demokrat.>243</Česká str.sociálně demokrat.>
    <Radostné Česko>2</Radostné Česko>
    <STAROSTOVÉ A NEZÁVISLÍ>127</STAROSTOVÉ A NEZÁVISLÍ>
    <Komunistická str.Čech a Moravy>243</Komunistická str.Čech a Moravy>
    <Strana zelených>16</Strana zelených>
    <ROZUMNÍ-stop migraci,diktát.EU>13</ROZUMNÍ-stop migraci,diktát.EU>
    <Strana svobodných občanů>17</Strana svobodných občanů>
    <Blok proti islam.-Obran.domova>3</Blok proti islam.-Obran.domova>
    <Občanská demokratická aliance>2</Občanská demokratická aliance>
    <Česká pirátská strana>158</Česká pirátská strana>
    <Česká národní fronta>1</Česká národní fronta>
    <Referendum o Evropské unii>0</Referendum o Evropské unii>
    <TOP 09>33</TOP 09>
    <ANO 2011>968</ANO 2011>
    <Dobrá volba 2016>0</Dobrá volba 2016>
    <SPR-Republ.str.Čsl. M.Sládka>5</SPR-Republ.str.Čsl. M.Sládka>
    <Křesť.demokr.unie-Čs.str.lid.>140</Křesť.demokr.unie-Čs.str.lid.>
    <Česká strana národně sociální>2</Česká strana národně sociální>
    <REALISTÉ>7</REALISTÉ>
    <SPORTOVCI>1</SPORTOVCI>
    <Dělnic.str.sociální spravedl.>7</Dělnic.str.sociální spravedl.>
    <Svob.a př.dem.-T.Okamura (SPD)>385</Svob.a př.dem.-T.Okamura (SPD)>
    <Strana Práv Občanů>11</Strana Práv Občanů>
  </obec>
  <obec>
    <Číslo obce>568864</Číslo obce>
    <Název obce>Doubrava</Název obce>
    <Voliči>1013</Voliči>
    <Vydané obálky>526</Vydané obálky>
    <Platné hlasy>526</Platné hlasy>
    <Občanská demokratická strana>14</Občanská demokratická strana>
    <Řád národa - Vlastenecká unie>4</Řád národa - Vlastenecká unie>
    <CESTA ODPOVĚDNÉ SPOLEČNOSTI>2</CESTA ODPOVĚDNÉ SPOLEČNOSTI>
    <Česká str.sociálně demokrat.>40</Česká str.sociálně demokrat.>
    <Radostné Česko>0</Radostné Česko>
    <STAROSTOVÉ A NEZÁVISLÍ>9</STAROSTOVÉ A NEZÁVISLÍ>
    <Komunistická str.Čech a Moravy>62</Komunistická str.Čech a Moravy>
    <Strana zelených>3</Strana zelených>
    <ROZUMNÍ-stop migraci,diktát.EU>5</ROZUMNÍ-stop migraci,diktát.EU>
    <Strana svobodných občanů>4</Strana svobodných občanů>
    <Blok proti islam.-Obran.domova>0</Blok proti islam.-Obran.domova>
    <Občanská demokratická aliance>0</Občanská demokratická aliance>
    <Česká pirátská strana>34</Česká pirátská strana>
    <Česká národní fronta>0</Česká národní fronta>
    <Referendum o Evropské unii>0</Referendum o Evropské unii>
    <TOP 09>3</TOP 09>
    <ANO 2011>221</ANO 2011>
    <Dobrá volba 2016>0</Dobrá volba 2016>
    <SPR-Republ.str.Čsl. M.Sládka>0</SPR-Republ.str.Čsl. M.Sládka>
    <Křesť.demokr.unie-Čs.str.lid.>24</Křesť.demokr.unie-Čs.str.lid.>
    <Česká strana národně sociální>0</Česká strana národně sociální>
    <REALISTÉ>3</REALISTÉ>
    <SPORTOVCI>0</SPORTOVCI>
    <Dělnic.str.sociální spravedl.>2</Dělnic.str.sociální spravedl.>
    <Svob.a př.dem.-T.Okamura (SPD)>92</Svob.a př.dem.-T.Okamura (SPD)>
    <Strana Práv Občanů>4</Strana Práv Občanů>
  </obec>
  <obec>
    <Číslo obce>555088</Číslo obce>
    <Název obce>Havířov</Název obce>
    <Voliči>61372</Voliči>
    <Vydané obálky>31666</Vydané obálky>
    <Platné hlasy>31480</Platné hlasy>
    <Občanská demokratická strana>1699</Občanská demokratická strana>
    <Řád národa - Vlastenecká unie>60</Řád národa - Vlastenecká unie>
    <CESTA ODPOVĚDNÉ SPOLEČNOSTI>13</CESTA ODPOVĚDNÉ SPOLEČNOSTI>
    <Česká str.sociálně demokrat.>2996</Česká str.sociálně demokrat.>
    <Radostné Česko>23</Radostné Česko>
    <STAROSTOVÉ A NEZÁVISLÍ>629</STAROSTOVÉ A NEZÁVISLÍ>
    <Komunistická str.Čech a Moravy>3694</Komunistická str.Čech a Moravy>
    <Strana zelených>373</Strana zelených>
    <ROZUMNÍ-stop migraci,diktát.EU>207</ROZUMNÍ-stop migraci,diktát.EU>
    <Strana svobodných občanů>275</Strana svobodných občanů>
    <Blok proti islam.-Obran.domova>13</Blok proti islam.-Obran.domova>
    <Občanská demokratická aliance>71</Občanská demokratická aliance>
    <Česká pirátská strana>2657</Česká pirátská strana>
    <Česká národní fronta>4</Česká národní fronta>
    <Referendum o Evropské unii>23</Referendum o Evropské unii>
    <TOP 09>589</TOP 09>
    <ANO 2011>11596</ANO 2011>
    <Dobrá volba 2016>29</Dobrá volba 2016>
    <SPR-Republ.str.Čsl. M.Sládka>55</SPR-Republ.str.Čsl. M.Sládka>
    <Křesť.demokr.unie-Čs.str.lid.>1154</Křesť.demokr.unie-Čs.str.lid.>
    <Česká strana národně sociální>17</Česká strana národně sociální>
    <REALISTÉ>186</REALISTÉ>
    <SPORTOVCI>44</SPORTOVCI>
    <Dělnic.str.sociální spravedl.>52</Dělnic.str.sociální spravedl.>
    <Svob.a př.dem.-T.Okamura (SPD)>4904</Svob.a př.dem.-T.Okamura (SPD)>
    <Strana Práv Občanů>117</Strana Práv Občanů>
  </obec>
  <obec>
    <Číslo obce>598178</Číslo obce>
    <Název obce>Horní Bludovice</Název obce>
    <Voliči>1930</Voliči>
    <Vydané obálky>1294</Vydané obálky>
    <Platné hlasy>1288</Platné hlasy>
    <Občanská demokratická strana>116</Občanská demokratická strana>
    <Řád národa - Vlastenecká unie>5</Řád národa - Vlastenecká unie>
    <CESTA ODPOVĚDNÉ SPOLEČNOSTI>1</CESTA ODPOVĚDNÉ SPOLEČNOSTI>
    <Česká str.sociálně demokrat.>85</Česká str.sociálně demokrat.>
    <Radostné Česko>1</Radostné Česko>
    <STAROSTOVÉ A NEZÁVISLÍ>42</STAROSTOVÉ A NEZÁVISLÍ>
    <Komunistická str.Čech a Moravy>171</Komunistická str.Čech a Moravy>
    <Strana zelených>14</Strana zelených>
    <ROZUMNÍ-stop migraci,diktát.EU>7</ROZUMNÍ-stop migraci,diktát.EU>
    <Strana svobodných občanů>9</Strana svobodných občanů>
    <Blok proti islam.-Obran.domova>1</Blok proti islam.-Obran.domova>
    <Občanská demokratická aliance>3</Občanská demokratická aliance>
    <Česká pirátská strana>132</Česká pirátská strana>
    <Česká národní fronta>1</Česká národní fronta>
    <Referendum o Evropské unii>0</Referendum o Evropské unii>
    <TOP 09>27</TOP 09>
    <ANO 2011>419</ANO 2011>
    <Dobrá volba 2016>0</Dobrá volba 2016>
    <SPR-Republ.str.Čsl. M.Sládka>4</SPR-Republ.str.Čsl. M.Sládka>
    <Křesť.demokr.unie-Čs.str.lid.>91</Křesť.demokr.unie-Čs.str.lid.>
    <Česká strana národně sociální>0</Česká strana národně sociální>
    <REALISTÉ>10</REALISTÉ>
    <SPORTOVCI>2</SPORTOVCI>
    <Dělnic.str.sociální spravedl.>2</Dělnic.str.sociální spravedl.>
    <Svob.a př.dem.-T.Okamura (SPD)>143</Svob.a př.dem.-T.Okamura (SPD)>
    <Strana Práv Občanů>2</Strana Práv Občanů>
  </obec>
  <obec>
    <Číslo obce>552739</Číslo obce>
    <Název obce>Horní Suchá</Název obce>
    <Voliči>3628</Voliči>
    <Vydané obálky>1908</Vydané obálky>
    <Platné hlasy>1902</Platné hlasy>
    <Občanská demokratická strana>82</Občanská demokratická strana>
    <Řád národa - Vlastenecká unie>2</Řád národa - Vlastenecká unie>
    <CESTA ODPOVĚDNÉ SPOLEČNOSTI>0</CESTA ODPOVĚDNÉ SPOLEČNOSTI>
    <Česká str.sociálně demokrat.>164</Česká str.sociálně demokrat.>
    <Radostné Česko>1</Radostné Česko>
    <STAROSTOVÉ A NEZÁVISLÍ>180</STAROSTOVÉ A NEZÁVISLÍ>
    <Komunistická str.Čech a Moravy>197</Komunistická str.Čech a Moravy>
    <Strana zelených>19</Strana zelených>
    <ROZUMNÍ-stop migraci,diktát.EU>7</ROZUMNÍ-stop migraci,diktát.EU>
    <Strana svobodných občanů>22</Strana svobodných občanů>
    <Blok proti islam.-Obran.domova>1</Blok proti islam.-Obran.domova>
    <Občanská demokratická aliance>2</Občanská demokratická aliance>
    <Česká pirátská strana>135</Česká pirátská strana>
    <Česká národní fronta>0</Česká národní fronta>
    <Referendum o Evropské unii>1</Referendum o Evropské unii>
    <TOP 09>31</TOP 09>
    <ANO 2011>629</ANO 2011>
    <Dobrá volba 2016>0</Dobrá volba 2016>
    <SPR-Republ.str.Čsl. M.Sládka>3</SPR-Republ.str.Čsl. M.Sládka>
    <Křesť.demokr.unie-Čs.str.lid.>122</Křesť.demokr.unie-Čs.str.lid.>
    <Česká strana národně sociální>0</Česká strana národně sociální>
    <REALISTÉ>10</REALISTÉ>
    <SPORTOVCI>0</SPORTOVCI>
    <Dělnic.str.sociální spravedl.>2</Dělnic.str.sociální spravedl.>
    <Svob.a př.dem.-T.Okamura (SPD)>287</Svob.a př.dem.-T.Okamura (SPD)>
    <Strana Práv Občanů>5</Strana Práv Občanů>
  </obec>
  <obec>
    <Číslo obce>555291</Číslo obce>
    <Název obce>Chotěbuz</Název obce>
    <Voliči>1000</Voliči>
    <Vydané obálky>634</Vydané obálky>
    <Platné hlasy>634</Platné hlasy>
    <Občanská demokratická strana>33</Občanská demokratická strana>
    <Řád národa - Vlastenecká unie>1</Řád národa - Vlastenecká unie>
    <CESTA ODPOVĚDNÉ SPOLEČNOSTI>0</CESTA ODPOVĚDNÉ SPOLEČNOSTI>
    <Česká str.sociálně demokrat.>51</Česká str.sociálně demokrat.>
    <Radostné Česko>0</Radostné Česko>
    <STAROSTOVÉ A NEZÁVISLÍ>7</STAROSTOVÉ A NEZÁVISLÍ>
    <Komunistická str.Čech a Moravy>48</Komunistická str.Čech a Moravy>
    <Strana zelených>4</Strana zelených>
    <ROZUMNÍ-stop migraci,diktát.EU>9</ROZUMNÍ-stop migraci,diktát.EU>
    <Strana svobodných občanů>5</Strana svobodných občanů>
    <Blok proti islam.-Obran.domova>0</Blok proti islam.-Obran.domova>
    <Občanská demokratická aliance>0</Občanská demokratická aliance>
    <Česká pirátská strana>48</Česká pirátská strana>
    <Česká národní fronta>0</Česká národní fronta>
    <Referendum o Evropské unii>0</Referendum o Evropské unii>
    <TOP 09>5</TOP 09>
    <ANO 2011>189</ANO 2011>
    <Dobrá volba 2016>0</Dobrá volba 2016>
    <SPR-Republ.str.Čsl. M.Sládka>1</SPR-Republ.str.Čsl. M.Sládka>
    <Křesť.demokr.unie-Čs.str.lid.>118</Křesť.demokr.unie-Čs.str.lid.>
    <Česká strana národně sociální>0</Česká strana národně sociální>
    <REALISTÉ>5</REALISTÉ>
    <SPORTOVCI>1</SPORTOVCI>
    <Dělnic.str.sociální spravedl.>1</Dělnic.str.sociální spravedl.>
    <Svob.a př.dem.-T.Okamura (SPD)>107</Svob.a př.dem.-T.Okamura (SPD)>
    <Strana Práv Občanů>1</Strana Práv Občanů>
  </obec>
  <obec>
    <Číslo obce>598917</Číslo obce>
    <Název obce>Karviná</Název obce>
    <Voliči>45014</Voliči>
    <Vydané obálky>21136</Vydané obálky>
    <Platné hlasy>21025</Platné hlasy>
    <Občanská demokratická strana>900</Občanská demokratická strana>
    <Řád národa - Vlastenecká unie>34</Řád národa - Vlastenecká unie>
    <CESTA ODPOVĚDNÉ SPOLEČNOSTI>8</CESTA ODPOVĚDNÉ SPOLEČNOSTI>
    <Česká str.sociálně demokrat.>2422</Česká str.sociálně demokrat.>
    <Radostné Česko>30</Radostné Česko>
    <STAROSTOVÉ A NEZÁVISLÍ>328</STAROSTOVÉ A NEZÁVISLÍ>
    <Komunistická str.Čech a Moravy>2365</Komunistická str.Čech a Moravy>
    <Strana zelených>166</Strana zelených>
    <ROZUMNÍ-stop migraci,diktát.EU>151</ROZUMNÍ-stop migraci,diktát.EU>
    <Strana svobodných občanů>116</Strana svobodných občanů>
    <Blok proti islam.-Obran.domova>20</Blok proti islam.-Obran.domova>
    <Občanská demokratická aliance>7</Občanská demokratická aliance>
    <Česká pirátská strana>1206</Česká pirátská strana>
    <Česká národní fronta>1</Česká národní fronta>
    <Referendum o Evropské unii>24</Referendum o Evropské unii>
    <TOP 09>262</TOP 09>
    <ANO 2011>8426</ANO 2011>
    <Dobrá volba 2016>20</Dobrá volba 2016>
    <SPR-Republ.str.Čsl. M.Sládka>61</SPR-Republ.str.Čsl. M.Sládka>
    <Křesť.demokr.unie-Čs.str.lid.>747</Křesť.demokr.unie-Čs.str.lid.>
    <Česká strana národně sociální>7</Česká strana národně sociální>
    <REALISTÉ>52</REALISTÉ>
    <SPORTOVCI>21</SPORTOVCI>
    <Dělnic.str.sociální spravedl.>38</Dělnic.str.sociální spravedl.>
    <Svob.a př.dem.-T.Okamura (SPD)>3540</Svob.a př.dem.-T.Okamura (SPD)>
    <Strana Práv Občanů>73</Strana Práv Občanů>
  </obec>
  <obec>
    <Číslo obce>599069</Číslo obce>
    <Název obce>Orlová</Název obce>
    <Voliči>24736</Voliči>
    <Vydané obálky>11313</Vydané obálky>
    <Platné hlasy>11257</Platné hlasy>
    <Občanská demokratická strana>548</Občanská demokratická strana>
    <Řád národa - Vlastenecká unie>11</Řád národa - Vlastenecká unie>
    <CESTA ODPOVĚDNÉ SPOLEČNOSTI>2</CESTA ODPOVĚDNÉ SPOLEČNOSTI>
    <Česká str.sociálně demokrat.>1022</Česká str.sociálně demokrat.>
    <Radostné Česko>10</Radostné Česko>
    <STAROSTOVÉ A NEZÁVISLÍ>186</STAROSTOVÉ A NEZÁVISLÍ>
    <Komunistická str.Čech a Moravy>1251</Komunistická str.Čech a Moravy>
    <Strana zelených>82</Strana zelených>
    <ROZUMNÍ-stop migraci,diktát.EU>92</ROZUMNÍ-stop migraci,diktát.EU>
    <Strana svobodných občanů>91</Strana svobodných občanů>
    <Blok proti islam.-Obran.domova>20</Blok proti islam.-Obran.domova>
    <Občanská demokratická aliance>3</Občanská demokratická aliance>
    <Česká pirátská strana>696</Česká pirátská strana>
    <Česká národní fronta>4</Česká národní fronta>
    <Referendum o Evropské unii>10</Referendum o Evropské unii>
    <TOP 09>123</TOP 09>
    <ANO 2011>4651</ANO 2011>
    <Dobrá volba 2016>11</Dobrá volba 2016>
    <SPR-Republ.str.Čsl. M.Sládka>32</SPR-Republ.str.Čsl. M.Sládka>
    <Křesť.demokr.unie-Čs.str.lid.>304</Křesť.demokr.unie-Čs.str.lid.>
    <Česká strana národně sociální>6</Česká strana národně sociální>
    <REALISTÉ>32</REALISTÉ>
    <SPORTOVCI>12</SPORTOVCI>
    <Dělnic.str.sociální spravedl.>16</Dělnic.str.sociální spravedl.>
    <Svob.a př.dem.-T.Okamura (SPD)>1909</Svob.a př.dem.-T.Okamura (SPD)>
    <Strana Práv Občanů>133</Strana Práv Občanů>
  </obec>
  <obec>
    <Číslo obce>599077</Číslo obce>
    <Název obce>Petrovice u Karviné</Název obce>
    <Voliči>4014</Voliči>
    <Vydané obálky>2470</Vydané obálky>
    <Platné hlasy>2460</Platné hlasy>
    <Občanská demokratická strana>164</Občanská demokratická strana>
    <Řád národa - Vlastenecká unie>1</Řád národa - Vlastenecká unie>
    <CESTA ODPOVĚDNÉ SPOLEČNOSTI>1</CESTA ODPOVĚDNÉ SPOLEČNOSTI>
    <Česká str.sociálně demokrat.>223</Česká str.sociálně demokrat.>
    <Radostné Česko>3</Radostné Česko>
    <STAROSTOVÉ A NEZÁVISLÍ>50</STAROSTOVÉ A NEZÁVISLÍ>
    <Komunistická str.Čech a Moravy>187</Komunistická str.Čech a Moravy>
    <Strana zelených>29</Strana zelených>
    <ROZUMNÍ-stop migraci,diktát.EU>19</ROZUMNÍ-stop migraci,diktát.EU>
    <Strana svobodných občanů>18</Strana svobodných občanů>
    <Blok proti islam.-Obran.domova>1</Blok proti islam.-Obran.domova>
    <Občanská demokratická aliance>5</Občanská demokratická aliance>
    <Česká pirátská strana>193</Česká pirátská strana>
    <Česká národní fronta>0</Česká národní fronta>
    <Referendum o Evropské unii>1</Referendum o Evropské unii>
    <TOP 09>49</TOP 09>
    <ANO 2011>954</ANO 2011>
    <Dobrá volba 2016>0</Dobrá volba 2016>
    <SPR-Republ.str.Čsl. M.Sládka>3</SPR-Republ.str.Čsl. M.Sládka>
    <Křesť.demokr.unie-Čs.str.lid.>188</Křesť.demokr.unie-Čs.str.lid.>
    <Česká strana národně sociální>0</Česká strana národně sociální>
    <REALISTÉ>8</REALISTÉ>
    <SPORTOVCI>1</SPORTOVCI>
    <Dělnic.str.sociální spravedl.>4</Dělnic.str.sociální spravedl.>
    <Svob.a př.dem.-T.Okamura (SPD)>349</Svob.a př.dem.-T.Okamura (SPD)>
    <Strana Práv Občanů>9</Strana Práv Občanů>
  </obec>
  <obec>
    <Číslo obce>599085</Číslo obce>
    <Název obce>Petřvald</Název obce>
    <Voliči>5860</Voliči>
    <Vydané obálky>3048</Vydané obálky>
    <Platné hlasy>3029</Platné hlasy>
    <Občanská demokratická strana>181</Občanská demokratická strana>
    <Řád národa - Vlastenecká unie>6</Řád národa - Vlastenecká unie>
    <CESTA ODPOVĚDNÉ SPOLEČNOSTI>3</CESTA ODPOVĚDNÉ SPOLEČNOSTI>
    <Česká str.sociálně demokrat.>320</Česká str.sociálně demokrat.>
    <Radostné Česko>4</Radostné Česko>
    <STAROSTOVÉ A NEZÁVISLÍ>65</STAROSTOVÉ A NEZÁVISLÍ>
    <Komunistická str.Čech a Moravy>419</Komunistická str.Čech a Moravy>
    <Strana zelených>19</Strana zelených>
    <ROZUMNÍ-stop migraci,diktát.EU>17</ROZUMNÍ-stop migraci,diktát.EU>
    <Strana svobodných občanů>19</Strana svobodných občanů>
    <Blok proti islam.-Obran.domova>4</Blok proti islam.-Obran.domova>
    <Občanská demokratická aliance>3</Občanská demokratická aliance>
    <Česká pirátská strana>182</Česká pirátská strana>
    <Česká národní fronta>1</Česká národní fronta>
    <Referendum o Evropské unii>4</Referendum o Evropské unii>
    <TOP 09>45</TOP 09>
    <ANO 2011>1087</ANO 2011>
    <Dobrá volba 2016>3</Dobrá volba 2016>
    <SPR-Republ.str.Čsl. M.Sládka>5</SPR-Republ.str.Čsl. M.Sládka>
    <Křesť.demokr.unie-Čs.str.lid.>86</Křesť.demokr.unie-Čs.str.lid.>
    <Česká strana národně sociální>1</Česká strana národně sociální>
    <REALISTÉ>22</REALISTÉ>
    <SPORTOVCI>7</SPORTOVCI>
    <Dělnic.str.sociální spravedl.>5</Dělnic.str.sociální spravedl.>
    <Svob.a př.dem.-T.Okamura (SPD)>510</Svob.a př.dem.-T.Okamura (SPD)>
    <Strana Práv Občanů>11</Strana Práv Občanů>
  </obec>
  <obec>
    <Číslo obce>599107</Číslo obce>
    <Název obce>Rychvald</Název obce>
    <Voliči>5963</Voliči>
    <Vydané obálky>3467</Vydané obálky>
    <Platné hlasy>3444</Platné hlasy>
    <Občanská demokratická strana>220</Občanská demokratická strana>
    <Řád národa - Vlastenecká unie>2</Řád národa - Vlastenecká unie>
    <CESTA ODPOVĚDNÉ SPOLEČNOSTI>3</CESTA ODPOVĚDNÉ SPOLEČNOSTI>
    <Česká str.sociálně demokrat.>304</Česká str.sociálně demokrat.>
    <Radostné Česko>2</Radostné Česko>
    <STAROSTOVÉ A NEZÁVISLÍ>68</STAROSTOVÉ A NEZÁVISLÍ>
    <Komunistická str.Čech a Moravy>342</Komunistická str.Čech a Moravy>
    <Strana zelených>39</Strana zelených>
    <ROZUMNÍ-stop migraci,diktát.EU>10</ROZUMNÍ-stop migraci,diktát.EU>
    <Strana svobodných občanů>31</Strana svobodných občanů>
    <Blok proti islam.-Obran.domova>5</Blok proti islam.-Obran.domova>
    <Občanská demokratická aliance>3</Občanská demokratická aliance>
    <Česká pirátská strana>261</Česká pirátská strana>
    <Česká národní fronta>0</Česká národní fronta>
    <Referendum o Evropské unii>1</Referendum o Evropské unii>
    <TOP 09>75</TOP 09>
    <ANO 2011>1398</ANO 2011>
    <Dobrá volba 2016>3</Dobrá volba 2016>
    <SPR-Republ.str.Čsl. M.Sládka>13</SPR-Republ.str.Čsl. M.Sládka>
    <Křesť.demokr.unie-Čs.str.lid.>88</Křesť.demokr.unie-Čs.str.lid.>
    <Česká strana národně sociální>1</Česká strana národně sociální>
    <REALISTÉ>17</REALISTÉ>
    <SPORTOVCI>9</SPORTOVCI>
    <Dělnic.str.sociální spravedl.>8</Dělnic.str.sociální spravedl.>
    <Svob.a př.dem.-T.Okamura (SPD)>523</Svob.a př.dem.-T.Okamura (SPD)>
    <Strana Práv Občanů>18</Strana Práv Občanů>
  </obec>
  <obec>
    <Číslo obce>599140</Číslo obce>
    <Název obce>Stonava</Název obce>
    <Voliči>1473</Voliči>
    <Vydané obálky>910</Vydané obálky>
    <Platné hlasy>904</Platné hlasy>
    <Občanská demokratická strana>20</Občanská demokratická strana>
    <Řád národa - Vlastenecká unie>2</Řád národa - Vlastenecká unie>
    <CESTA ODPOVĚDNÉ SPOLEČNOSTI>0</CESTA ODPOVĚDNÉ SPOLEČNOSTI>
    <Česká str.sociálně demokrat.>67</Česká str.sociálně demokrat.>
    <Radostné Česko>0</Radostné Česko>
    <STAROSTOVÉ A NEZÁVISLÍ>28</STAROSTOVÉ A NEZÁVISLÍ>
    <Komunistická str.Čech a Moravy>85</Komunistická str.Čech a Moravy>
    <Strana zelených>6</Strana zelených>
    <ROZUMNÍ-stop migraci,diktát.EU>6</ROZUMNÍ-stop migraci,diktát.EU>
    <Strana svobodných občanů>3</Strana svobodných občanů>
    <Blok proti islam.-Obran.domova>0</Blok proti islam.-Obran.domova>
    <Občanská demokratická aliance>1</Občanská demokratická aliance>
    <Česká pirátská strana>66</Česká pirátská strana>
    <Česká národní fronta>0</Česká národní fronta>
    <Referendum o Evropské unii>0</Referendum o Evropské unii>
    <TOP 09>18</TOP 09>
    <ANO 2011>398</ANO 2011>
    <Dobrá volba 2016>0</Dobrá volba 2016>
    <SPR-Republ.str.Čsl. M.Sládka>3</SPR-Republ.str.Čsl. M.Sládka>
    <Křesť.demokr.unie-Čs.str.lid.>73</Křesť.demokr.unie-Čs.str.lid.>
    <Česká strana národně sociální>1</Česká strana národně sociální>
    <REALISTÉ>0</REALISTÉ>
    <SPORTOVCI>1</SPORTOVCI>
    <Dělnic.str.sociální spravedl.>1</Dělnic.str.sociální spravedl.>
    <Svob.a př.dem.-T.Okamura (SPD)>124</Svob.a př.dem.-T.Okamura (SPD)>
    <Strana Práv Občanů>1</Strana Práv Občanů>
  </obec>
  <obec>
    <Číslo obce>599158</Číslo obce>
    <Název obce>Těrlicko</Název obce>
    <Voliči>3661</Voliči>
    <Vydané obálky>2389</Vydané obálky>
    <Platné hlasy>2374</Platné hlasy>
    <Občanská demokratická strana>171</Občanská demokratická strana>
    <Řád národa - Vlastenecká unie>5</Řád národa - Vlastenecká unie>
    <CESTA ODPOVĚDNÉ SPOLEČNOSTI>1</CESTA ODPOVĚDNÉ SPOLEČNOSTI>
    <Česká str.sociálně demokrat.>205</Česká str.sociálně demokrat.>
    <Radostné Česko>0</Radostné Česko>
    <STAROSTOVÉ A NEZÁVISLÍ>56</STAROSTOVÉ A NEZÁVISLÍ>
    <Komunistická str.Čech a Moravy>237</Komunistická str.Čech a Moravy>
    <Strana zelených>30</Strana zelených>
    <ROZUMNÍ-stop migraci,diktát.EU>17</ROZUMNÍ-stop migraci,diktát.EU>
    <Strana svobodných občanů>17</Strana svobodných občanů>
    <Blok proti islam.-Obran.domova>5</Blok proti islam.-Obran.domova>
    <Občanská demokratická aliance>2</Občanská demokratická aliance>
    <Česká pirátská strana>170</Česká pirátská strana>
    <Česká národní fronta>2</Česká národní fronta>
    <Referendum o Evropské unii>5</Referendum o Evropské unii>
    <TOP 09>59</TOP 09>
    <ANO 2011>863</ANO 2011>
    <Dobrá volba 2016>5</Dobrá volba 2016>
    <SPR-Republ.str.Čsl. M.Sládka>4</SPR-Republ.str.Čsl. M.Sládka>
    <Křesť.demokr.unie-Čs.str.lid.>203</Křesť.demokr.unie-Čs.str.lid.>
    <Česká strana národně sociální>1</Česká strana národně sociální>
    <REALISTÉ>10</REALISTÉ>
    <SPORTOVCI>3</SPORTOVCI>
    <Dělnic.str.sociální spravedl.>3</Dělnic.str.sociální spravedl.>
    <Svob.a př.dem.-T.Okamura (SPD)>297</Svob.a př.dem.-T.Okamura (SPD)>
    <Strana Práv Občanů>3</Strana Práv Občanů>
  </obec>
</vysledky>